log_telegram/__init__.py
log_telegram/handlers.py
log_telegram-0.2.dist-info/LICENSE
log_telegram-0.2.dist-info/METADATA
log_telegram-0.2.dist-info/WHEEL
log_telegram-0.2.dist-info/top_level.txt
log_telegram-0.2.dist-info/RECORD
